j5_zoloto/__init__.py
j5_zoloto/backends.py
j5_zoloto/board.py
j5_zoloto/component.py
j5_zoloto/py.typed
j5_zoloto-0.4.0.dist-info/LICENSE
j5_zoloto-0.4.0.dist-info/WHEEL
j5_zoloto-0.4.0.dist-info/METADATA
j5_zoloto-0.4.0.dist-info/RECORD
