Metadata-Version: 2.1
Name: j5-zoloto
Version: 0.4.0
Summary: j5 integration for Zoloto computer vision
Home-page: https://github.com/j5api/j5-zoloto
License: MIT
Author: j5 contributors
Author-email: j5api@googlegroups.com
Requires-Python: >=3.8,<4.0
Classifier: Development Status :: 4 - Beta
Classifier: License :: OSI Approved :: MIT License
Classifier: Operating System :: OS Independent
Classifier: Programming Language :: Python :: 3
Classifier: Programming Language :: Python :: 3.10
Classifier: Programming Language :: Python :: 3.8
Classifier: Programming Language :: Python :: 3.9
Classifier: Topic :: Education
Classifier: Topic :: Software Development :: Libraries :: Python Modules
Classifier: Typing :: Typed
Requires-Dist: j5 (>=1.0.0,<2.0.0)
Requires-Dist: zoloto (>=0.9.0,<0.10.0)
Project-URL: Repository, https://github.com/j5api/j5-zoloto
